<?xml version="1.0" encoding="iso-8859-1"?>

<root version="3.0">
  <properties>
    <name>5E - Matjam's Status Indicators</name>
    <version>1.0</version>
  	<loadorder>2000</loadorder>
    <author>matjam</author>
    <description>Show the status of a PC or NPC on the battlemap using graphical icon overlays.</description>
  </properties>

  <announcement text="5E - Matjam's Save Indicators version 1.0" font="emotefont" icon="MatjamsExtension" />

  <base>
    <icon name="MatjamsExtension" file="matjam.png"></icon>
		<includefile source="graphics/graphics_icons.xml" />

    <string name="option_header_matjams_status_indicators">Matjam's Status Indicators</string>
    <string name="option_label_MJSI_ENABLED">Enable Indicators</string>

    <script name="MatjamsStatusIndicators" file="scripts/status_indicators.lua" />
  </base>
</root>
